transformerx/__init__.py
transformerx/layers/__init__.py
transformerx/layers/addnorm.py
transformerx/layers/dot_product_attention.py
transformerx/layers/multihead_attention.py
transformerx/layers/positional_encoding.py
transformerx/layers/positionwise_ffn.py
transformerx/layers/transformer_decoder.py
transformerx/layers/transformer_decoder_block.py
transformerx/layers/transformer_encoder.py
transformerx/layers/transformer_encoder_block.py
transformerx/txplot/__init__.py
transformerx/txplot/plot_pe.py
transformerx-1.0.0b1.dist-info/LICENSE
transformerx-1.0.0b1.dist-info/WHEEL
transformerx-1.0.0b1.dist-info/METADATA
transformerx-1.0.0b1.dist-info/RECORD
