Metadata-Version: 2.1
Name: transformerx
Version: 1.0.0b1
Summary: TransformerX is a python library for building transformer-based models using ready-to-use layers.
Home-page: https://github.com/tensorops/TransformerX
License: Apache
Keywords: transformer,deep-learning,machine-learning,NLP,natural-language-processing,computer-vision,cv,vision,speech-recognition
Author: Soran Ghaderi
Author-email: soran.gdr.cs@gmail.com
Maintainer: Soran Ghaderi
Maintainer-email: soran.gdr.cs@gmail.com
Requires-Python: >=3.10,<3.11
Classifier: Development Status :: 4 - Beta
Classifier: Intended Audience :: Developers
Classifier: Intended Audience :: Education
Classifier: Intended Audience :: Science/Research
Classifier: License :: OSI Approved :: BSD License
Classifier: License :: Other/Proprietary License
Classifier: Operating System :: OS Independent
Classifier: Programming Language :: Python :: 3
Classifier: Programming Language :: Python :: 3.10
Classifier: Programming Language :: Python :: 3.11
Classifier: Programming Language :: Python :: 3.6
Classifier: Programming Language :: Python :: 3.7
Classifier: Programming Language :: Python :: 3.8
Classifier: Programming Language :: Python :: 3.9
Classifier: Topic :: Scientific/Engineering
Classifier: Topic :: Scientific/Engineering :: Artificial Intelligence
Classifier: Topic :: Scientific/Engineering :: Mathematics
Classifier: Topic :: Software Development
Classifier: Topic :: Software Development :: Libraries
Classifier: Topic :: Software Development :: Libraries :: Python Modules
Requires-Dist: einops (>=0.4.1,<0.5.0)
Requires-Dist: matplotlib (>=3.5.3,<4.0.0)
Requires-Dist: numpy (>=1.23.2,<2.0.0)
Requires-Dist: pytest (>=7.1.2,<8.0.0)
Requires-Dist: tensorflow (>=2.9.0,<3.0.0)
Project-URL: Repository, https://github.com/tensorops/TransformerX
